farmworld/__init__.py
farmworld/const/__init__.py
farmworld/env/__init__.py
farmworld/geojson/__init__.py
farmworld/geojson/example1.json
farmworld/geojson/example2.json
farmworld/geojson/util/__init__.py
farmworld/renderer/__init__.py
farmworld/types/__init__.py
farmworld-0.0.3.dist-info/WHEEL
farmworld-0.0.3.dist-info/METADATA
farmworld-0.0.3.dist-info/RECORD
